{"n04429376": "throne", "n04464125": "track", "n02870880": "bookcase", "n10085101": "fence", "n04326896": "stool", "n02818832": "bed", "n10768903": "washer", "n04463679": "track, rail, rails, runway", "n02732072": "aquarium, fish_tank, marine_museum", "n04522168": "vase", "n14844693": "soil, dirt", "n03642806": "laptop, laptop_computer", "n06277280": "television, telecasting, TV, video", "n04162433": "seat", "n06262943": "silver_screen", "n02912065": "buffet, counter, sideboard", "n02708224": "analog_computer, analogue_computer", "n04330340": "stove, kitchen_stove, range, kitchen_range, cooking_stove", "n04233124": "skyscraper", "n02775897": "Bailey_bridge", "n02883344": "box", "n03976657": "pole", "n12102133": "grass", "n03723153": "marquee, marquise", "n11669921": "flower", "n04314914": "step, stair", "n00474568": "ball", "n03002096": "chair", "n03545150": "house", "n02828884": "bench", "n00449517": "auto_racing, car_racing", "n04161358": "seat", "n03221720": "door", "n03938244": "pillow", "n03531281": "hood", "n03941417": "pinball_machine, pin_table", "n09416076": "rock, stone", "n02788148": "bannister, banister, balustrade, balusters, handrail", "n04217882": "signboard, sign", "n02958343": "car, auto, automobile, machine, motorcar", "n02834778": "bicycle, bike, wheel, cycle", "n04546855": "wall", "n03320046": "fan", "n03173929": "delivery_truck, delivery_van, panel_truck", "n09303008": "hill", "n04190052": "shelf", "n00439826": "track_and_field", "n03619890": "kitchen", "n03100897": "conveyer_belt, conveyor_belt, conveyer, conveyor, transporter", "n03148324": "cupboard, closet", "n03699975": "machine", "n04152387": "screen", "n02691156": "airplane, aeroplane, plane", "n04070727": "refrigerator, icebox", "n02952109": "canopy", "n04460130": "tower", "n09436708": "sky", "n02778669": "ball", "n04476259": "tray", "n03005285": "chandelier, pendant, pendent", "n02795528": "barrel, gun_barrel", "n04215402": "sidewalk, pavement", "n04547592": "wall", "n04474035": "transporter, car_transporter", "n15019030": "sand", "n04388743": "tank, storage_tank", "n04461879": "toy", "n04296562": "stage", "n09403211": "radiator", "n03544360": "house", "n04446276": "toilet, lavatory, lav, can, john, privy, bathroom", "n03782190": "monitor, monitoring_device", "n04096066": "road, route", "n02763901": "awning, sunshade, sunblind", "n03982430": "pool_table, billiard_table, snooker_table", "n04587648": "window", "n02874086": "booth", "n09330378": "lake_bed, lake_bottom", "n04040759": "radiator", "n09260907": "cultivated_land, farmland, plowland, ploughland, tilled_land, tillage, tilth", "n02797692": "base, pedestal, stand", "n03438257": "glass, drinking_glass", "n04373704": "swivel_chair", "n03365592": "floor, flooring", "n03550289": "hutch", "n04041069": "radiator", "n03125729": "cradle", "n00440039": "track, running", "n02952237": "canopy", "n09415584": "riverbank, riverside", "n09248399": "coastland", "n04298661": "stairwell", "n02951843": "canopy", "n03531447": "hood", "n04389033": "tank, army_tank, armored_combat_vehicle, armoured_combat_vehicle", "n02998563": "cesspool, cesspit, sink, sump", "n03531691": "hood", "n02706806": "amusement_arcade", "n13156986": "palmate_leaf", "n03990474": "pot", "n02974697": "case", "n02808440": "bathtub, bathing_tub, bath, tub", "n03151077": "curtain, drape, drapery, mantle, pall", "n04194289": "ship", "n04335886": "streetlight, street_lamp", "n03207941": "dishwasher, dish_washer, dishwashing_machine", "n03960490": "plate", "n03346455": "fireplace, hearth, open_fireplace", "n10478960": "proctor, monitor", "n03773035": "mirror", "n02873839": "booth, cubicle, stall, kiosk", "n00017222": "plant, flora, plant_life", "n06874185": "traffic_light, traffic_signal, stoplight", "n03636248": "lamp", "n02933112": "cabinet", "n04574999": "wheel", "n04490091": "truck, motortruck", "n04118021": "rug, carpet, carpeting", "n07935504": "water", "n03354903": "flag", "n02924116": "bus, autobus, coach, charabanc, double-decker, jitney, motorbus, motorcoach, omnibus, passenger_vehicle", "n03528901": "home_plate, home_base, home, plate", "n02796995": "barroom, bar, saloon, ginmill, taproom", "n07579787": "plate", "n02874214": "booth", "n04411264": "tent, collapsible_shelter", "n03327234": "fence, fencing", "n03082979": "computer, computing_machine, computing_device, data_processor, electronic_computer, information_processing_system", "n04520170": "van", "n09331251": "lakefront", "n03100346": "convertible, sofa_bed", "n03769722": "minibike, motorbike", "n04379243": "table", "n04153025": "screen_door, screen", "n03782006": "monitor", "n03074380": "column, pillar", "n04148579": "sconce", "n02930645": "byway, bypath, byroad", "n04047401": "railing, rail", "n04459362": "towel", "n04330267": "stove", "n09282208": "floor", "n03620353": "kitchenette", "n03862676": "oven", "n03238586": "dressing_table, dresser, vanity, toilet_table", "n03342127": "finger-painting", "n04151581": "screen", "n02851099": "blind, screen", "n02975212": "case, display_case, showcase, vitrine", "n02898711": "bridge, span", "n03636649": "lamp", "n03781787": "monitor", "n03933933": "pier", "n09359803": "mountain, mount", "n03085602": "computer_screen, computer_display", "n04047733": "railing", "n04157320": "sculpture", "n03046257": "clock", "n02747177": "ashcan, trash_can, garbage_can, wastebin, ash_bin, ash-bin, ashbin, dustbin, trash_barrel, trash_bin", "n09214060": "bar", "n08645104": "scrubland", "n02990373": "ceiling", "n03547054": "hovel, hut, hutch, shack, shanty", "n03931044": "picture, image, icon, ikon", "n04550184": "wardrobe, closet, press", "n04151940": "screen, cover, covert, concealment", "n04299370": "stall", "n03222318": "door", "n00015388": "animal, animate_being, beast, brute, creature, fauna", "n02774152": "bag, handbag, pocketbook, purse", "n09474412": "wall", "n02819697": "bed", "n03858418": "ottoman, pouf, pouffe, puff, hassock", "n02738535": "armchair", "n02773838": "bag, traveling_bag, travelling_bag, grip, suitcase", "n03015254": "chest_of_drawers, chest, bureau, dresser", "n03977158": "pole", "n03380724": "footstool, footrest, ottoman, tuffet", "n03531546": "hood, exhaust_hood", "n02946921": "can, tin, tin_can", "n13104059": "tree", "n03991062": "pot, flowerpot", "n09931640": "coach, manager, handler", "n02773037": "bag", "n03550153": "hut, army_hut, field_hut", "n03001627": "chair", "n02779435": "ball", "n03366464": "floor", "n03222176": "door", "n07576182": "buffet", "n03956922": "plant, works, industrial_plant", "n02858304": "boat", "n03236735": "dress, frock", "n03116530": "counter", "n09415671": "riverbed, river_bottom", "n04208936": "shower", "n02788689": "bar", "n03063968": "coffee_table, cocktail_table", "n03438661": "glass", "n03073977": "column, pillar", "n14564779": "wall", "n04554684": "washer, automatic_washer, washing_machine", "n03226880": "double_door", "n02789487": "bar", "n04198797": "shock_absorber, shock, cushion", "n02913152": "building, edifice", "n04161981": "seat", "n03761084": "microwave, microwave_oven", "n04379964": "table", "n03117199": "counter", "n02806992": "bathhouse, bathing_machine", "n02377703": "saddle_horse, riding_horse, mount", "n02870526": "book", "n03790512": "motorcycle, bike", "n02726681": "apartment_building, apartment_house", "n09332890": "lakeside, lakeshore", "n00470966": "rugby, rugby_football, rugger", "n03388043": "fountain", "n04405907": "television_receiver, television, television_set, tv, tv_set, idiot_box, boob_tube, telly, goggle_box", "n03273913": "electric_refrigerator, fridge", "n04555400": "washstand, wash-hand_stand", "n02876657": "bottle", "n03179701": "desk", "n00007846": "person, individual, someone, somebody, mortal, soul", "n08598301": "grassland", "n01319467": "marine_animal, marine_creature, sea_animal, sea_creature", "n02728440": "apparel, wearing_apparel, dress, clothes", "n01317541": "domestic_animal, domesticated_animal", "n08659446": "field", "n12582231": "palm, palm_tree", "n02806530": "bath", "n02849154": "blanket, cover", "n03665366": "light, light_source", "n01055165": "camping, encampment, bivouacking, tenting", "n02801938": "basket, handbasket", "n03934042": "pier", "n04120842": "runway", "n00021265": "food, nutrient", "n04148703": "sconce", "n04256520": "sofa, couch, lounge", "n03462747": "ground, earth", "n04554871": "washer"}